nexatestlib/__init__.py
nexatestlib/multiplication.py
nexatestlib-0.1.0.dist-info/METADATA
nexatestlib-0.1.0.dist-info/WHEEL
nexatestlib-0.1.0.dist-info/top_level.txt
nexatestlib-0.1.0.dist-info/RECORD
