Metadata-Version: 2.1
Name: nexatestlib
Version: 0.1.0
Summary: NexaTestLib
Author: Alex
License: MIT
Requires-Dist: numpy
